Metadata-Version: 1.0
Name: custom-wordcloud-generator
Version: 0.6
Summary: Slightly modified Muellers Wordcloud generator
Home-page: UNKNOWN
Author: UNKNOWN
Author-email: ekertdenis@gmail.com
License: UNKNOWN
Platform: UNKNOWN
